{
	"level1": {
		"projectile_speed": "1",
		"projectile_scale": "1",
		"projectile_count": "2"
	},
	"level2": {
		"projectile_speed": "1",
		"projectile_scale": "1.1",
		"projectile_count": "3"
	},
	"level3": {
		"projectile_speed": "2",
		"projectile_scale": "1.2",
		"projectile_count": "4"
	},
	"level4": {
		"projectile_speed": "2",
		"projectile_scale": "1.3",
		"projectile_count": "5"
	},
	"level5": {
		"projectile_speed": "3",
		"projectile_scale": "1.4",
		"projectile_count": "6"
	},
	"level6": {
		"projectile_speed": "4",
		"projectile_scale": "1.5",
		"projectile_count": "8"
	}
}
